tello_renewal/__init__.py
tello_renewal/__main__.py
tello_renewal/cli/__init__.py
tello_renewal/cli/commands.py
tello_renewal/core/__init__.py
tello_renewal/core/engine.py
tello_renewal/core/models.py
tello_renewal/core/renewer.py
tello_renewal/core/services/__init__.py
tello_renewal/core/services/account.py
tello_renewal/core/services/balance.py
tello_renewal/core/services/renewal.py
tello_renewal/notification/__init__.py
tello_renewal/notification/email.py
tello_renewal/utils/__init__.py
tello_renewal/utils/cache.py
tello_renewal/utils/config.py
tello_renewal/utils/exceptions.py
tello_renewal/utils/logging.py
tello_renewal/web/__init__.py
tello_renewal/web/client.py
tello_renewal/web/driver.py
tello_renewal/web/elements/__init__.py
tello_renewal/web/elements/locators.py
tello_renewal/web/pages/__init__.py
tello_renewal/web/pages/base.py
tello_renewal/web/pages/dashboard.py
tello_renewal/web/pages/login.py
tello_renewal/web/pages/renewal.py
tello_renewal-0.2.1.dist-info/licenses/LICENSE
tello_renewal-0.2.1.dist-info/METADATA
tello_renewal-0.2.1.dist-info/WHEEL
tello_renewal-0.2.1.dist-info/entry_points.txt
tello_renewal-0.2.1.dist-info/top_level.txt
tello_renewal-0.2.1.dist-info/RECORD
