Metadata-Version: 2.4
Name: tello-renewal
Version: 0.2.1
Summary: Tello mobile plan automatic renewal system
Author-email: Oaklight <oaklight@gmx.com>
License: MIT
Project-URL: Homepage, https://github.com/Oaklight/tello-renewal
Project-URL: Repository, https://github.com/Oaklight/tello-renewal
Project-URL: Documentation, https://github.com/Oaklight/tello-renewal#readme
Project-URL: Bug Tracker, https://github.com/Oaklight/tello-renewal/issues
Keywords: tello,mobile,renewal,automation,selenium
Classifier: Development Status :: 4 - Beta
Classifier: Intended Audience :: End Users/Desktop
Classifier: License :: OSI Approved :: MIT License
Classifier: Operating System :: OS Independent
Classifier: Programming Language :: Python :: 3
Classifier: Programming Language :: Python :: 3.10
Classifier: Programming Language :: Python :: 3.11
Classifier: Programming Language :: Python :: 3.12
Classifier: Topic :: Communications :: Telephony
Classifier: Topic :: Office/Business :: Financial
Classifier: Topic :: System :: Systems Administration
Requires-Python: >=3.10
License-File: LICENSE
Requires-Dist: pydantic>=2.10.0
Requires-Dist: pydantic-settings>=2.7.0
Requires-Dist: selenium>=4.27.0
Requires-Dist: tomli>=2.0.0; python_version < "3.11"
Requires-Dist: typing-extensions>=4.0.0; python_version < "3.11"
Requires-Dist: loguru>=0.7.0
Requires-Dist: pytz>=2023.3
Provides-Extra: dev
Requires-Dist: pytest>=7.0.0; extra == "dev"
Requires-Dist: pytest-cov>=4.0.0; extra == "dev"
Requires-Dist: ruff>=0.1.0; extra == "dev"
Requires-Dist: pyright>=1.1.0; extra == "dev"
Requires-Dist: pre-commit>=3.0.0; extra == "dev"
Requires-Dist: build>=1.0.0; extra == "dev"
Requires-Dist: twine>=4.0.0; extra == "dev"
Provides-Extra: test
Requires-Dist: pytest>=7.0.0; extra == "test"
Requires-Dist: pytest-cov>=4.0.0; extra == "test"
Requires-Dist: pytest-mock>=3.10.0; extra == "test"
Requires-Dist: selenium>=4.27.0; extra == "test"
Dynamic: license-file
